{
    "german": {
        "page": "/aisad-ob-ge",
        "header_menu_1": "Haftungsausschluss",
        "header_menu_2": "Datenschutzbestimmungen",
        "header_menu_3": "Werben sie mit uns",
        "header_menu_4": "Impressum",
        "category_menu_1": "Gesundheit",
        "category_menu_2": "Fitness",
        "category_menu_3": "Sport"
    },
    "partugal": {
        "page": "/agedif-ob-pr",
        "header_menu_1": "Isenção de Responsabilidade",
        "header_menu_2": "Política de Privacidade",
        "header_menu_3": "Anuncie Conosco",
        "header_menu_4": "Impressum",
        "category_menu_1": "Saúde",
        "category_menu_2": "Fitness",
        "category_menu_3": "Esportes"
    }

}